{
  "meta": {
    "name": "프림",
    "cv": "윤은서",
    "rarity": "SSR",
    "squad": "카페 스위티",
    "company": "어브노멀",
    "class": "지원형",
    "burst": "I",
    "code": "철갑",
    "weapon": "저격소총 (SR)"
  },
  "stats": {
    "combatPower": 1950,
    "hp": 98250,
    "atk": 1800,
    "def": 599
  },
  "skills": {
    "skill1": 1,
    "skill2": 1,
    "burst": 1
  },
  "cube": {
    "level": 0
  },
  "collection": {
    "rarity": "R",
    "skillLv1": 1,
    "skillLv2": 1
  },
  "equipment": [],
  "rawUrl": "https://www.blablalink.com/shiftyspad/nikke?from=list&nikke=142",
  "timestamp": "2026-01-13T21:57:36.845Z"
}